vid2led/__init__.py
vid2led/__main__.py
vid2led/cli.py
vid2led/matrix.py
vid2led/util.py
vid2led-0.1.3.dist-info/entry_points.txt
vid2led-0.1.3.dist-info/LICENSE
vid2led-0.1.3.dist-info/METADATA
vid2led-0.1.3.dist-info/WHEEL
vid2led-0.1.3.dist-info/RECORD
